{
  "user": [
    {
      "id": "halloo",
      "password": "halloo"
    },
    {
      "id": "IchBinEinKek",
      "password": "Amogus12345#"
    }
  ],
  "threads": [
    {
      "author": "IchBinEinKek",
      "dateMessage": "1",
      "question": "Any1",
      "createdAt": "4.5.2023",
      "questionContent": "watwatwatwatwatwatwatwatwatwatwatwatwatwatwatwatwatwatwatwatwatwatwatwat",
      "id": 1
    },
    {
      "author": "IchBinEinKek",
      "dateMessage": "2",
      "question": "NeuerThreadAMogus",
      "createdAt": "4.5.2023",
      "questionContent": "",
      "id": 2
    },
    {
      "author": "IchBinEinKek",
      "dateMessage": "3",
      "question": "PArade",
      "createdAt": "4.5.2023",
      "questionContent": "",
      "id": 3
    },
    {
      "author": "IchBinEinKek",
      "dateMessage": "4",
      "question": "Sosa",
      "createdAt": "4.5.2023",
      "questionContent": "",
      "id": 4
    }
  ]
}